agiflow/__init__.py
agiflow/agiflow.py
agiflow/config/__init__.py
agiflow/config/constants.py
agiflow/config/environment_vars.py
agiflow/opentelemetry/.DS_Store
agiflow/opentelemetry/__init__.py
agiflow/opentelemetry/context/__init__.py
agiflow/opentelemetry/context/constants.py
agiflow/opentelemetry/context/context.py
agiflow/opentelemetry/context/context_propagation.py
agiflow/opentelemetry/context/span_from_context.py
agiflow/opentelemetry/convention/__init__.py
agiflow/opentelemetry/convention/agiflow_attributes.py
agiflow/opentelemetry/convention/constants.py
agiflow/opentelemetry/convention/database_span_attributes.py
agiflow/opentelemetry/convention/framework_span_attributes.py
agiflow/opentelemetry/convention/gen_ai_span_attributes.py
agiflow/opentelemetry/convention/gen_ai_span_events.py
agiflow/opentelemetry/convention/llm_span_attributes.py
agiflow/opentelemetry/instrumentation/__init__.py
agiflow/opentelemetry/instrumentation/anthropic/__init__.py
agiflow/opentelemetry/instrumentation/anthropic/hooks/__init__.py
agiflow/opentelemetry/instrumentation/anthropic/hooks/base.py
agiflow/opentelemetry/instrumentation/anthropic/hooks/message_create.py
agiflow/opentelemetry/instrumentation/anthropic/instrumentation.py
agiflow/opentelemetry/instrumentation/chroma/__init__.py
agiflow/opentelemetry/instrumentation/chroma/hooks/__init__.py
agiflow/opentelemetry/instrumentation/chroma/hooks/base.py
agiflow/opentelemetry/instrumentation/chroma/hooks/collection_call.py
agiflow/opentelemetry/instrumentation/chroma/instrumentation.py
agiflow/opentelemetry/instrumentation/cohere/__init__.py
agiflow/opentelemetry/instrumentation/cohere/hooks/__init__.py
agiflow/opentelemetry/instrumentation/cohere/hooks/base.py
agiflow/opentelemetry/instrumentation/cohere/hooks/base_chat.py
agiflow/opentelemetry/instrumentation/cohere/hooks/chat_create.py
agiflow/opentelemetry/instrumentation/cohere/hooks/chat_stream.py
agiflow/opentelemetry/instrumentation/cohere/hooks/embed.py
agiflow_sdk-0.0.24.dist-info/LICENSE
agiflow_sdk-0.0.24.dist-info/METADATA
agiflow_sdk-0.0.24.dist-info/WHEEL
agiflow_sdk-0.0.24.dist-info/RECORD
